{
    "web": {
        "client_id": "671996679896-nqj912dcsbeoitmgtrvscv6am5uck3tg.apps.googleusercontent.com",
        "project_id": "healthercise-test",
        "auth_uri": "https://accounts.google.com/o/oauth2/auth",
        "token_uri": "https://oauth2.googleapis.com/token",
        "auth_provider_x509_cert_url": "https://www.googleapis.com/oauth2/v1/certs",
        "client_secret": "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",
        "redirect_uris": [
            "http://localhost:3000",
            "http://localhost",
            "http://localhost:3000/auth/callback",
            "http://localhost/auth/callback",
            "https://api.healthercise.k1h.dev/auth/callback",
            "http://localhost:8000",
            "http://localhost:8000/auth/callback"
        ],
        "javascript_origins": [
            "http://localhost:3000",
            "http://localhost",
            "https://api.healthercise.k1h.dev",
            "http://localhost:8000"
        ]
    }
}